[
  {
    "page_content": "People / Alumni\n\n#### Maggie Wu\n\n#### Hometown\n\nChina\n\n#### Current city\n\nChicago, IL\n\n#### What is your current job?\n\nData scientist at QuantumBlack, AI by McKinsey\n\n#### What were you doing before you started the master’s program?\n\nFinancial Analyst\n\n#### What were the top factors that went into your decision to choose the MS in Applied Data Science Program at UChicago?\n\nThe program has solid reputation in data science industry. It also provides innovative curriculums that integrate advanced topics and trends in the field.\n\n#### What was one of your favorite aspects of being a student at UChicago?\n\nThe faculty at UChicago creates a diverse and inclusive environment where students from various backgrounds felt valued and empowered to excel.\n\n#### In your view, how has the MS in Applied Data Science degree advanced your career so far?\n\nThe program advanced my career by providing systematic learning structure, practical project experience, and inspiring discussion environment. The degree also helped me open doors to new opportunities.\n\n#### What was one of your favorite classes you took at UChicago and why?\n\nBig data platform is one of my favorite classes because it provides a comprehensive overview of m advanced technology infrastructures, which is very difficult to grasp without the instructors’ guidance and insights. It builds my foundations of the big data exploration.\n\n#### What do you enjoy doing outside of work?\n\nReading, museums, YouTube\n\n#### What excites you right now about the field of data science?\n\nWith the emergence of Generative AI, I consider myself fortunate as a data scientist to have the opportunity to delve into this exciting and cutting-edge field.\n\n#### What advice would you give to prospective students who are seeking a master’s degree in data science?\n\nLeverage the opportunity of starting a new journey. Don’t limit yourself on what you known, but explore on the unknowns. Discover your true intent and passion. You will derive greater satisfaction, motivation, and focus!",
    "metadata": {
      "title": "Maggie Wu – DSI",
      "original_url": "https://datascience.uchicago.edu/people/maggie-wu",
      "category": "people",
      "date": "2025-05-04",
      "source_file": "C:\\Users\\alen.pavlovic\\Documents\\GitLab\\gen-ai-midterm-project\\data\\markdown_clean_final\\people_maggie-wu.md",
      "filename": "people_maggie-wu.md",
      "chunk_id": "people_maggie-wu_0",
      "section_level": "document"
    }
  }
]